energy_toolkit/logger.py
energy_toolkit/msr_reader.cpython-38-x86_64-linux-gnu.so
energy_toolkit/util.py
energy_toolkit/rapl_interface.py
energy_toolkit/cli.py
energy_toolkit/plotter.py
energy_toolkit/config_parser.py
energy_toolkit/energy_toolkit.py
energy_toolkit/program.py
energy_toolkit/__init__.py
energy_toolkit-1.0.6.dist-info/LICENSE
energy_toolkit-1.0.6.dist-info/WHEEL
energy_toolkit-1.0.6.dist-info/entry_points.txt
energy_toolkit-1.0.6.dist-info/top_level.txt
energy_toolkit-1.0.6.dist-info/METADATA
energy_toolkit-1.0.6.dist-info/RECORD
