Metadata-Version: 2.1
Name: energy-toolkit
Version: 1.0.6
Summary: Provides functionality to benchmark a program and measure time and energy during execution.
Home-page: https://github.com/printerboi/energy-toolkit
Author: Maximilian Krebs, Ben Hermann
Author-email: maximilian.krebs@cs.tu-dortmund.de
Classifier: Programming Language :: Python :: 3
Classifier: Operating System :: OS Independent
Requires-Python: >=3.6
License-File: LICENSE
Requires-Dist: numpy >=1.18.0
Requires-Dist: py-cpuinfo >=9.0.0
Requires-Dist: click >=8.3.0
Requires-Dist: PyYAML >=6.0.3
Requires-Dist: plotly >=6.3.1
Requires-Dist: kaleido >=1.1.0
